{
  "$schema": "https://ui.shadcn.com/schema/registry-item.json",
  "name": "button-08",
  "title": "Button Demo",
  "description": "Example showing a simple button.",
  "registryDependencies": [
    "button"
  ],
  "files": [
    {
      "path": "examples/button/button-08.tsx",
      "content": "\"use client\"\n\nimport { Moon } from \"@aliimam/icons\"\nimport { motion } from \"motion/react\"\n\nimport { cn } from \"@/lib/utils\"\nimport { Button } from \"@/components/ui/button\"\n\nexport default function ButtonDemo() {\n  return (\n    <div className=\"flex gap-3\">\n      <Button size={\"icon-lg\"} variant={\"outline\"} className=\"relative\">\n        <div\n          className={cn(\n            \"border-inset pointer-events-none absolute -inset-px rounded-[inherit] border-2 border-transparent [mask-clip:padding-box,border-box]\",\n            \"[mask-image:linear-gradient(transparent,transparent),linear-gradient(#000,#000)] [mask-composite:intersect]\"\n          )}\n        >\n          <motion.div\n            className={cn(\n              \"via-primary to-primary absolute aspect-square bg-gradient-to-r from-transparent\"\n            )}\n            animate={{\n              offsetDistance: [\"0%\", \"100%\"],\n            }}\n            style={{\n              width: 20,\n              offsetPath: `rect(0 auto auto 0 round ${20}px)`,\n            }}\n            transition={{\n              repeat: Number.POSITIVE_INFINITY,\n              duration: 5,\n              ease: \"linear\",\n            }}\n          />\n        </div>\n        <Moon />\n      </Button>\n\n      <Button size={\"lg\"} variant={\"outline\"} className=\"relative\">\n        <div\n          className={cn(\n            \"border-inset pointer-events-none absolute -inset-px rounded-[inherit] border-2 border-transparent [mask-clip:padding-box,border-box]\",\n            \"[mask-image:linear-gradient(transparent,transparent),linear-gradient(#000,#000)] [mask-composite:intersect]\"\n          )}\n        >\n          <motion.div\n            className={cn(\n              \"via-primary to-primary absolute aspect-square bg-gradient-to-r from-transparent\"\n            )}\n            animate={{\n              offsetDistance: [\"0%\", \"100%\"],\n            }}\n            style={{\n              width: 20,\n              offsetPath: `rect(0 auto auto 0 round ${20}px)`,\n            }}\n            transition={{\n              repeat: Number.POSITIVE_INFINITY,\n              duration: 5,\n              ease: \"linear\",\n            }}\n          />\n        </div>\n        Animated Border\n      </Button>\n    </div>\n  )\n}\n",
      "type": "registry:example"
    }
  ],
  "type": "registry:example"
}