{
  "$schema": "https://ui.shadcn.com/schema/registry-item.json",
  "name": "note-text_rounded",
  "type": "registry:ui",
  "title": "Note Text",
  "description": "Note Text icon component",
  "category": "document",
  "tags": [],
  "dependencies": [],
  "devDependencies": [],
  "registryDependencies": [],
  "files": [
    {
      "path": "registry/icons/document/note-text_rounded.tsx",
      "content": "/** Auto-generated - Do not edit */\n'use client';\nimport React from 'react';\n\nexport interface NoteTextRoundedProps extends React.SVGProps<SVGSVGElement> {\n  size?: number | string;\n  strokeWidth?: number;\n}\n\nexport const NoteTextRounded = React.forwardRef<SVGSVGElement, NoteTextRoundedProps>(\n  ({ size = 24, className = '', strokeWidth = 1, ...props }, ref) => (\n    <svg \n      ref={ref}\n      width={size}\n      height={size} \n      viewBox=\"0 0 24 24\"\n      fill=\"none\"\n      stroke=\"currentColor\"\n      className={className}\n      xmlns=\"http://www.w3.org/2000/svg\"\n      {...(strokeWidth !== undefined ? { strokeWidth } : {})}\n      {...props}\n    >\n      <path d=\"M8 2V5\"   strokeMiterlimit=\"10\" strokeLinecap=\"round\" strokeLinejoin=\"round\"/>\n<path d=\"M16 2V5\"   strokeMiterlimit=\"10\" strokeLinecap=\"round\" strokeLinejoin=\"round\"/>\n<path d=\"M21 8.5V17C21 20 19.5 22 16 22H8C4.5 22 3 20 3 17V8.5C3 5.5 4.5 3.5 8 3.5H16C19.5 3.5 21 5.5 21 8.5Z\"   strokeMiterlimit=\"10\" strokeLinecap=\"round\" strokeLinejoin=\"round\"/>\n<path d=\"M8 11H16\"   strokeMiterlimit=\"10\" strokeLinecap=\"round\" strokeLinejoin=\"round\"/>\n<path d=\"M8 16H12\"   strokeMiterlimit=\"10\" strokeLinecap=\"round\" strokeLinejoin=\"round\"/>\n    </svg>\n  )\n);\nNoteTextRounded.displayName = \"NoteTextRounded\";\nexport const NoteTextRoundedMetadata = { \n  id: \"note-text_rounded\", \n  baseId: \"note-text\", \n  variant: \"rounded\", \n  name: \"Note Text\", \n  category: \"document\", \n  tags: [], \n  viewBox: \"0 0 24 24\" \n} as const;\n\nexport default NoteTextRounded;\n",
      "type": "registry:ui"
    }
  ]
}
