{
  "$schema": "https://ui.shadcn.com/schema/registry-item.json",
  "name": "paint-roller",
  "type": "registry:ui",
  "title": "Paint Roller",
  "description": "Paint Roller icon component",
  "category": "design",
  "tags": [],
  "dependencies": [],
  "devDependencies": [],
  "registryDependencies": [],
  "files": [
    {
      "path": "registry/icons/design/paint-roller.tsx",
      "content": "/** Auto-generated - Do not edit */\n'use client';\nimport React from 'react';\n\nexport interface PaintRollerProps extends React.SVGProps<SVGSVGElement> {\n  size?: number | string;\n  strokeWidth?: number;\n}\n\nexport const PaintRoller = React.forwardRef<SVGSVGElement, PaintRollerProps>(\n  ({ size = 24, className = '', strokeWidth = 1, ...props }, ref) => (\n    <svg \n      ref={ref}\n      width={size}\n      height={size} \n      viewBox=\"0 0 24 24\"\n      fill=\"none\"\n      stroke=\"currentColor\"\n      className={className}\n      xmlns=\"http://www.w3.org/2000/svg\"\n      {...(strokeWidth !== undefined ? { strokeWidth } : {})}\n      {...props}\n    >\n      <rect width=\"16\" height=\"6\" x=\"2\" y=\"2\" rx=\"2\" />\n  <path d=\"M10 16v-2a2 2 0 0 1 2-2h8a2 2 0 0 0 2-2V7a2 2 0 0 0-2-2h-2\" />\n  <rect width=\"4\" height=\"6\" x=\"8\" y=\"16\" rx=\"1\" />\n    </svg>\n  )\n);\nPaintRoller.displayName = \"PaintRoller\";\nexport const PaintRollerMetadata = { \n  id: \"paint-roller\", \n  baseId: \"paint-roller\", \n  variant: \"default\", \n  name: \"Paint Roller\", \n  category: \"design\", \n  tags: [], \n  viewBox: \"0 0 24 24\" \n} as const;\n\nexport default PaintRoller;\n",
      "type": "registry:ui"
    }
  ]
}
