{
  "$schema": "https://ui.shadcn.com/schema/registry-item.json",
  "name": "square-library",
  "type": "registry:ui",
  "title": "Square Library",
  "description": "Square Library icon component",
  "category": "square",
  "tags": [],
  "dependencies": [],
  "devDependencies": [],
  "registryDependencies": [],
  "files": [
    {
      "path": "registry/icons/square/square-library.tsx",
      "content": "/** Auto-generated - Do not edit */\n'use client';\nimport React from 'react';\n\nexport interface SquareLibraryProps extends React.SVGProps<SVGSVGElement> {\n  size?: number | string;\n  strokeWidth?: number;\n}\n\nexport const SquareLibrary = React.forwardRef<SVGSVGElement, SquareLibraryProps>(\n  ({ size = 24, className = '', strokeWidth = 1, ...props }, ref) => (\n    <svg \n      ref={ref}\n      width={size}\n      height={size} \n      viewBox=\"0 0 24 24\"\n      fill=\"none\"\n      stroke=\"currentColor\"\n      className={className}\n      xmlns=\"http://www.w3.org/2000/svg\"\n      {...(strokeWidth !== undefined ? { strokeWidth } : {})}\n      {...props}\n    >\n      <rect width=\"18\" height=\"18\" x=\"3\" y=\"3\" rx=\"2\" />\n  <path d=\"M7 7v10\" />\n  <path d=\"M11 7v10\" />\n  <path d=\"m15 7 2 10\" />\n    </svg>\n  )\n);\nSquareLibrary.displayName = \"SquareLibrary\";\nexport const SquareLibraryMetadata = { \n  id: \"square-library\", \n  baseId: \"square-library\", \n  variant: \"default\", \n  name: \"Square Library\", \n  category: \"square\", \n  tags: [], \n  viewBox: \"0 0 24 24\" \n} as const;\n\nexport default SquareLibrary;\n",
      "type": "registry:ui"
    }
  ]
}