{
  "$schema": "https://ui.shadcn.com/schema/registry-item.json",
  "name": "toggle-on_rounded",
  "type": "registry:ui",
  "title": "Toggle On",
  "description": "Toggle On icon component",
  "category": "app",
  "tags": [],
  "dependencies": [],
  "devDependencies": [],
  "registryDependencies": [],
  "files": [
    {
      "path": "registry/icons/app/toggle-on_rounded.tsx",
      "content": "/** Auto-generated - Do not edit */\n'use client';\nimport React from 'react';\n\nexport interface ToggleOnRoundedProps extends React.SVGProps<SVGSVGElement> {\n  size?: number | string;\n  strokeWidth?: number;\n}\n\nexport const ToggleOnRounded = React.forwardRef<SVGSVGElement, ToggleOnRoundedProps>(\n  ({ size = 24, className = '', strokeWidth = 1, ...props }, ref) => (\n    <svg \n      ref={ref}\n      width={size}\n      height={size} \n      viewBox=\"0 0 24 24\"\n      fill=\"none\"\n      stroke=\"currentColor\"\n      className={className}\n      xmlns=\"http://www.w3.org/2000/svg\"\n      {...(strokeWidth !== undefined ? { strokeWidth } : {})}\n      {...props}\n    >\n      <path d=\"M13.3 16H15.7C17.7 16 18.5 15.2 18.5 13.2V10.8C18.5 8.8 17.7 8 15.7 8H13.3C11.3 8 10.5 8.8 10.5 10.8V13.2C10.5 15.2 11.3 16 13.3 16Z\"   strokeLinecap=\"round\" strokeLinejoin=\"round\"/>\n<path d=\"M17 20H7C3 20 2 19 2 15V9C2 5 3 4 7 4H17C21 4 22 5 22 9V15C22 19 21 20 17 20Z\"   strokeLinecap=\"round\" strokeLinejoin=\"round\"/>\n    </svg>\n  )\n);\nToggleOnRounded.displayName = \"ToggleOnRounded\";\nexport const ToggleOnRoundedMetadata = { \n  id: \"toggle-on_rounded\", \n  baseId: \"toggle-on\", \n  variant: \"rounded\", \n  name: \"Toggle On\", \n  category: \"app\", \n  tags: [], \n  viewBox: \"0 0 24 24\" \n} as const;\n\nexport default ToggleOnRounded;\n",
      "type": "registry:ui"
    }
  ]
}
