{
  "$schema": "https://ui.shadcn.com/schema/registry-item.json",
  "name": "utensils",
  "type": "registry:ui",
  "title": "Utensils",
  "description": "Utensils icon component",
  "category": "others",
  "tags": [],
  "dependencies": [],
  "devDependencies": [],
  "registryDependencies": [],
  "files": [
    {
      "path": "registry/icons/others/utensils.tsx",
      "content": "/** Auto-generated - Do not edit */\n'use client';\nimport React from 'react';\n\nexport interface UtensilsProps extends React.SVGProps<SVGSVGElement> {\n  size?: number | string;\n  strokeWidth?: number;\n}\n\nexport const Utensils = React.forwardRef<SVGSVGElement, UtensilsProps>(\n  ({ size = 24, className = '', strokeWidth = 1, ...props }, ref) => (\n    <svg \n      ref={ref}\n      width={size}\n      height={size} \n      viewBox=\"0 0 24 24\"\n      fill=\"none\"\n      stroke=\"currentColor\"\n      className={className}\n      xmlns=\"http://www.w3.org/2000/svg\"\n      {...(strokeWidth !== undefined ? { strokeWidth } : {})}\n      {...props}\n    >\n      <path d=\"M3 2v7c0 1.1.9 2 2 2h4a2 2 0 0 0 2-2V2\" />\n  <path d=\"M7 2v20\" />\n  <path d=\"M21 15V2a5 5 0 0 0-5 5v6c0 1.1.9 2 2 2h3Zm0 0v7\" />\n    </svg>\n  )\n);\nUtensils.displayName = \"Utensils\";\nexport const UtensilsMetadata = { \n  id: \"utensils\", \n  baseId: \"utensils\", \n  variant: \"default\", \n  name: \"Utensils\", \n  category: \"others\", \n  tags: [], \n  viewBox: \"0 0 24 24\" \n} as const;\n\nexport default Utensils;\n",
      "type": "registry:ui"
    }
  ]
}